<?xml version="1.0"?>
<definition id="IMACO7013" parentId="imaCulturalObject" type="object"> <!-- Photograph  -->
    <fields>
        <field name="rdf:type" type="URI" displayType="system" uri="rdf:type" dmsType="FORBIDDEN">
            <value>http://www.sirma.com/ontologies/2016/02/culturalHeritageConservation/IMA#Photograph</value>
        </field>
    </fields>
	
	<regions>
		<region id="generalCMSData" order="5" displayType="editable" label="ima.generalCMSData.region.label" >
			<fields>
				<field name="type" type="an..50" > 
					<value>IMACO7013</value>
				</field>
				
				<field name="photographMount" type="an..1800" displayType="editable" label="IMACO7013.photographMount.label" tooltip="IMACO7013.photographMount.tooltip" uri="ima:photographMount" />
				<field name="secondarySupportDescription" type="an..1800" displayType="editable" label="imaCulturalObject.secondarySupportDescription.label" tooltip="imaCulturalObject.secondarySupportDescription.tooltip" uri="ima:secondarySupportDescription" />
				<field name="primarySupportDescription" type="an..1800" displayType="editable" label="imaCulturalObject.primarySupportDescription.label" tooltip="imaCulturalObject.primarySupportDescription.tooltip" uri="ima:primarySupportDescription" />
				<field name="preparatoryLayer" type="an..1800" displayType="editable" label="IMACO7013.preparatoryLayer.label" tooltip="IMACO7013.preparatoryLayer.tooltip" uri="ima:preparatoryLayer" />
				<field name="mediaDescription" type="an..1800" displayType="editable" label="imaCulturalObject.mediaDescription.label" tooltip="imaCulturalObject.mediaDescription.tooltip" uri="ima:mediaDescription" />
				<field name="surfaceCoatingDescription" type="an..1800" displayType="editable" label="imaCulturalObject.surfaceCoatingDescription.label" tooltip="imaCulturalObject.surfaceCoatingDescription.tooltip" uri="ima:surfaceCoatingDescription" />
				<field name="auxiliaryComponents" type="an..1800" displayType="editable" label="imaCulturalObject.auxiliaryComponents.label" tooltip="imaCulturalObject.auxiliaryComponents.tooltip" uri="ima:auxiliaryComponents" />
				<field name="frameDescription" type="an..1800" displayType="editable" label="imaCulturalObject.frameDescription.label" tooltip="imaCulturalObject.frameDescription.tooltip" uri="ima:frameDescription" />
				<field name="glazingDescription" type="an..1800" displayType="editable" label="imaCulturalObject.glazingDescription.label" tooltip="imaCulturalObject.glazingDescription.tooltip" uri="ima:glazingDescription" />
				<field name="matType" type="an..1800" displayType="editable" label="imaCulturalObject.matType.label" tooltip="imaCulturalObject.matType.tooltip" uri="ima:matType" />
				<field name="displayDimensions" type="an..1800" displayType="editable" label="imaCulturalObject.displayDimensions.label" tooltip="imaCulturalObject.displayDimensions.tooltip" uri="ima:displayDimensions" >
					<condition id="readOnlyField" renderAs="READONLY">[integrated] IN ('true')</condition>
				</field>	
			</fields>	
		</region>
	</regions>
</definition>